deep_isin/__init__.py
deep_isin/isin.py
deep_isin-1.0.1.dist-info/METADATA
deep_isin-1.0.1.dist-info/WHEEL
deep_isin-1.0.1.dist-info/top_level.txt
deep_isin-1.0.1.dist-info/RECORD
