Metadata-Version: 2.4
Name: deep_isin
Version: 1.0.1
Summary: this checks key or value in dict(or list)
Author-email: howShouldIChosseMyUsername <trademark2179@gmail.com>
License: MIT
Requires-Python: >=3.7
